{"_id":{"$oid":"599708eb2d4fe129f1f39a6f"},"title":"Birds","startTime":{"$date":"2017-08-05T12:00:00.000Z"},"endTime":{"$date":"2017-08-05T13:00:00.000Z"},"admin":[],"preWork":[{"$oid":"597e7f912b559d06bf957ac4"},{"$oid":"597e7fa12b559d06bf957ac5"}],"instructors":[{"$oid":"597e7e3d2b559d06bf957abf"},{"$oid":"597e7e462b559d06bf957ac0"}],"__v":0}
{"_id":{"$oid":"59970a5bbbec1929fb608086"},"title":"Animals","startTime":{"$date":"2017-08-06T16:00:00.000Z"},"endTime":{"$date":"2017-08-06T20:00:00.000Z"},"admin":[],"preWork":[{"$oid":"59945c424bb50e1ea2a9aef6"}],"instructors":[{"$oid":"597e7e462b559d06bf957ac0"},{"$oid":"59927579867d8d1b2d9a8a53"}],"__v":0}
{"_id":{"$oid":"59af4f5167fa204bac492b50"},"title":"TestMessage","startTime":{"$date":"2017-09-07T15:00:00.000Z"},"endTime":{"$date":"2017-09-08T13:00:00.000Z"},"admin":[],"preWork":[],"instructors":[],"__v":0}
{"_id":{"$oid":"59b0be2846be184bcc7ee7fb"},"title":"Testing","startTime":{"$date":"2017-09-07T15:00:00.000Z"},"endTime":{"$date":"2017-09-07T16:00:00.000Z"},"admin":[],"preWork":[{"$oid":"59ad7bbd07eec9407a705b9a"}],"instructors":[{"$oid":"597e7e3d2b559d06bf957abf"}],"__v":0}
{"_id":{"$oid":"59b0c6f8a419995324997f5c"},"title":"Earliest session","startTime":{"$date":"2017-08-04T11:00:00.000Z"},"endTime":{"$date":"2017-08-04T11:30:00.000Z"},"admin":[],"preWork":[],"instructors":[{"$oid":"597e7e462b559d06bf957ac0"}],"__v":0}
{"_id":{"$oid":"59bb4189a7d7b189f81ad6e7"},"title":"Cats","startTime":{"$date":"2018-05-05T13:00:00.000Z"},"endTime":{"$date":"2018-05-05T14:00:00.000Z"},"admin":[],"preWork":[{"$oid":"59ad7bbd07eec9407a705b9a"}],"instructors":[{"$oid":"597e7e3d2b559d06bf957abf"}],"__v":0}
{"_id":{"$oid":"59bb42e7a7d7b189f81ad6ee"},"title":"Leadership in the World","startTime":{"$date":"2017-10-03T15:00:00.000Z"},"endTime":{"$date":"2017-10-03T18:00:00.000Z"},"admin":[],"preWork":[{"$oid":"59bb41e1a7d7b189f81ad6ea"}],"instructors":[{"$oid":"597e7e3d2b559d06bf957abf"}],"__v":0}
{"_id":{"$oid":"59bb4317a7d7b189f81ad6ef"},"title":"Influencing Everyone Around YOu","startTime":{"$date":"2017-10-03T18:00:00.000Z"},"endTime":{"$date":"2017-10-03T20:00:00.000Z"},"admin":[],"preWork":[{"$oid":"59bb420ca7d7b189f81ad6eb"}],"instructors":[{"$oid":"597e7e462b559d06bf957ac0"}],"__v":0}
{"_id":{"$oid":"59bb433ea7d7b189f81ad6f0"},"title":"Becoming the Best Leader","startTime":{"$date":"2017-10-03T21:00:00.000Z"},"endTime":{"$date":"2017-10-04T00:00:00.000Z"},"admin":[],"preWork":[{"$oid":"59bb422fa7d7b189f81ad6ec"}],"instructors":[{"$oid":"597e7e3d2b559d06bf957abf"}],"__v":0}
